bugster/__init__.py
bugster/auth/__init__.py
bugster/auth/base_login.py
bugster/auth/streategies.py
bugster/config/__init__.py
bugster/config/credentials.py
bugster/config/paths.py
bugster/core/__init__.py
bugster/core/base_page.py
bugster/core/bugster_context.py
bugster/core/bugster_expect.py
bugster/core/bugster_keyboard.py
bugster/core/bugster_mouse.py
bugster/core/custom_locator.py
bugster/core/dependency_manager.py
bugster/core/test_metadata.py
bugster/core/utils.py
bugster/exceptions/__init__.py
bugster/exceptions/login.py
bugster/reporting/__init__.py
bugster/reporting/screenshots.py
bugster/reporting/trace_viewer.py
bugster/test_runner/bugster_plugin.py
bugster/utils/__init__.py
bugster/utils/dummy_files.py
bugster/utils/random_utils.py
bugster-1.0.1.dist-info/METADATA
bugster-1.0.1.dist-info/WHEEL
bugster-1.0.1.dist-info/entry_points.txt
bugster-1.0.1.dist-info/RECORD
