Metadata-Version: 2.3
Name: bugster
Version: 1.0.1
Summary: Python-Playwright based testing framework for Bugster's e2e testing agent
License: MIT
Keywords: testing,bugster,playwright,pytest
Author: Naquiao
Author-email: nacho-solorzano@hotmail.com
Requires-Python: >=3.8,<4.0
Classifier: License :: OSI Approved :: MIT License
Classifier: Programming Language :: Python :: 3
Classifier: Programming Language :: Python :: 3.8
Classifier: Programming Language :: Python :: 3.9
Classifier: Programming Language :: Python :: 3.10
Classifier: Programming Language :: Python :: 3.11
Classifier: Programming Language :: Python :: 3.12
Classifier: Programming Language :: Python :: 3.13
Requires-Dist: playwright (>=1.49.0,<2.0.0)
Requires-Dist: pytest (>=8.3.4,<9.0.0)
Project-URL: Homepage, https://www.bugster.dev
Project-URL: Repository, https://github.com/Bugsterapp/bugster-framework
